ipyaml/__init__.py
ipyaml/api.py
ipyaml/cli.py
ipyaml/contents_manager.py
ipyaml/convert.py
ipyaml/tests/__init__.py
ipyaml/tests/test_cli.py
ipyaml/tests/test_convert.py
ipyaml-0.3.dist-info/DESCRIPTION.rst
ipyaml-0.3.dist-info/METADATA
ipyaml-0.3.dist-info/RECORD
ipyaml-0.3.dist-info/WHEEL
ipyaml-0.3.dist-info/entry_points.txt
ipyaml-0.3.dist-info/metadata.json
ipyaml-0.3.dist-info/top_level.txt
